setup.cfg
setup.py
sigma/__init__.py
sigma.core.egg-info/PKG-INFO
sigma.core.egg-info/SOURCES.txt
sigma.core.egg-info/dependency_links.txt
sigma.core.egg-info/namespace_packages.txt
sigma.core.egg-info/top_level.txt
sigma.core.egg-info/zip-safe
sigma/core/__init__.py
sigma/core/error.py
sigma/core/field.py
sigma/core/model.py
sigma/core/util.py
sigma/core/validator.py
test/test_asdict.py
test/test_field.py
test/test_model.py