Metadata-Version: 1.0
Name: sigma.core
Version: 0.5.0a0
Summary: Validation framework.
Home-page: https://github.com/pysigma/core
Author: Suzuki Shunsuke
Author-email: suzuki.shunsuke.1989@gmail.com
License: MIT
Keywords: validation
Platform: UNKNOWN
